{
  "memory_id": "7782aa42-b908-4e22-93db-63c86b0d5635",
  "trigger": {
    "task_family": "dynamic_recovery",
    "benchmark": "synthetic",
    "source_family": "debugging"
  },
  "recommended_schedule": [
    "researcher",
    "critic",
    "writer"
  ],
  "avoid": [
    {
      "action": "patch_before_reproduce"
    }
  ],
  "recommended_recovery": [],
  "recommended_policy_template": null,
  "confidence": 0.83,
  "supporting_episodes": [
    "seeded"
  ],
  "negative_cases": [],
  "last_updated": "2026-05-12T08:07:01.677663Z",
  "status": "active"
}